praval/__init__.py
praval/composition.py
praval/decorators.py
praval/tools.py
praval/core/__init__.py
praval/core/agent.py
praval/core/agent_runner.py
praval/core/exceptions.py
praval/core/reef.py
praval/core/reef_backend.py
praval/core/registry.py
praval/core/secure_reef.py
praval/core/secure_spore.py
praval/core/storage.py
praval/core/tool_registry.py
praval/core/transport.py
praval/memory/__init__.py
praval/memory/embedded_store.py
praval/memory/episodic_memory.py
praval/memory/long_term_memory.py
praval/memory/memory_manager.py
praval/memory/memory_types.py
praval/memory/semantic_memory.py
praval/memory/short_term_memory.py
praval/observability/__init__.py
praval/observability/config.py
praval/observability/export/__init__.py
praval/observability/export/console_viewer.py
praval/observability/export/otlp_exporter.py
praval/observability/instrumentation/__init__.py
praval/observability/instrumentation/manager.py
praval/observability/instrumentation/utils.py
praval/observability/storage/__init__.py
praval/observability/storage/sqlite_store.py
praval/observability/tracing/__init__.py
praval/observability/tracing/context.py
praval/observability/tracing/span.py
praval/observability/tracing/tracer.py
praval/providers/__init__.py
praval/providers/anthropic.py
praval/providers/cohere.py
praval/providers/factory.py
praval/providers/openai.py
praval/storage/__init__.py
praval/storage/base_provider.py
praval/storage/data_manager.py
praval/storage/decorators.py
praval/storage/exceptions.py
praval/storage/memory_integration.py
praval/storage/storage_registry.py
praval/storage/providers/__init__.py
praval/storage/providers/filesystem.py
praval/storage/providers/postgresql.py
praval/storage/providers/qdrant_provider.py
praval/storage/providers/redis_provider.py
praval/storage/providers/s3_provider.py
praval-0.7.20.dist-info/licenses/LICENSE
praval-0.7.20.dist-info/METADATA
praval-0.7.20.dist-info/WHEEL
praval-0.7.20.dist-info/top_level.txt
praval-0.7.20.dist-info/RECORD
