Metadata-Version: 2.4
Name: praval
Version: 0.7.20
Summary: A composable Python framework for LLM-based agents inspired by coral ecosystems
Author: Praval Team
License: MIT
Project-URL: Homepage, https://github.com/aiexplorations/praval
Project-URL: Documentation, https://github.com/aiexplorations/praval/tree/main/docs
Project-URL: Repository, https://github.com/aiexplorations/praval
Project-URL: Bug Tracker, https://github.com/aiexplorations/praval/issues
Project-URL: Changelog, https://github.com/aiexplorations/praval/blob/main/CHANGELOG.md
Keywords: ai,agents,llm,multi-agent,framework,openai,anthropic,cohere,rag,memory,vector-database,chromadb,qdrant,chatbot,knowledge-graph,semantic-search,nlp
Classifier: Development Status :: 3 - Alpha
Classifier: Intended Audience :: Developers
Classifier: License :: OSI Approved :: MIT License
Classifier: Programming Language :: Python :: 3
Classifier: Programming Language :: Python :: 3.9
Classifier: Programming Language :: Python :: 3.10
Classifier: Programming Language :: Python :: 3.11
Classifier: Programming Language :: Python :: 3.12
Classifier: Topic :: Scientific/Engineering :: Artificial Intelligence
Classifier: Topic :: Software Development :: Libraries :: Python Modules
Requires-Python: >=3.9
License-File: LICENSE
Requires-Dist: openai>=1.0.0
Requires-Dist: anthropic>=0.8.0
Requires-Dist: cohere>=4.0.0
Requires-Dist: pydantic>=2.0.0
Requires-Dist: pydantic-settings>=2.0.0
Requires-Dist: python-dotenv>=1.0.0
Provides-Extra: memory
Requires-Dist: chromadb>=0.4.0; extra == "memory"
Requires-Dist: sentence-transformers>=2.2.0; extra == "memory"
Requires-Dist: scikit-learn>=1.3.0; extra == "memory"
Provides-Extra: secure
Requires-Dist: aio-pika>=9.0.0; extra == "secure"
Requires-Dist: asyncio-mqtt>=0.16.0; extra == "secure"
Requires-Dist: aiostomp>=1.6.0; extra == "secure"
Requires-Dist: PyNaCl>=1.5.0; extra == "secure"
Requires-Dist: msgpack>=1.0.0; extra == "secure"
Provides-Extra: pdf
Requires-Dist: PyPDF2>=3.0.0; extra == "pdf"
Provides-Extra: storage
Requires-Dist: psycopg2-binary>=2.9.0; extra == "storage"
Requires-Dist: redis>=4.5.0; extra == "storage"
Requires-Dist: boto3>=1.26.0; extra == "storage"
Requires-Dist: qdrant-client>=1.6.0; extra == "storage"
Provides-Extra: docs
Requires-Dist: sphinx>=7.0.0; extra == "docs"
Requires-Dist: sphinx-rtd-theme>=2.0.0; extra == "docs"
Requires-Dist: sphinx-autodoc-typehints>=1.24.0; extra == "docs"
Requires-Dist: myst-parser>=2.0.0; extra == "docs"
Requires-Dist: sphinx-copybutton>=0.5.2; extra == "docs"
Requires-Dist: sphinx-design>=0.5.0; extra == "docs"
Provides-Extra: all
Requires-Dist: chromadb>=0.4.0; extra == "all"
Requires-Dist: sentence-transformers>=2.2.0; extra == "all"
Requires-Dist: scikit-learn>=1.3.0; extra == "all"
Requires-Dist: aio-pika>=9.0.0; extra == "all"
Requires-Dist: asyncio-mqtt>=0.16.0; extra == "all"
Requires-Dist: aiostomp>=1.6.0; extra == "all"
Requires-Dist: PyNaCl>=1.5.0; extra == "all"
Requires-Dist: msgpack>=1.0.0; extra == "all"
Requires-Dist: PyPDF2>=3.0.0; extra == "all"
Requires-Dist: psycopg2-binary>=2.9.0; extra == "all"
Requires-Dist: redis>=4.5.0; extra == "all"
Requires-Dist: boto3>=1.26.0; extra == "all"
Requires-Dist: qdrant-client>=1.6.0; extra == "all"
Provides-Extra: dev
Requires-Dist: pytest>=7.0.0; extra == "dev"
Requires-Dist: pytest-cov>=4.0.0; extra == "dev"
Requires-Dist: pytest-asyncio>=0.21.0; extra == "dev"
Requires-Dist: black>=23.0.0; extra == "dev"
Requires-Dist: isort>=5.12.0; extra == "dev"
Requires-Dist: flake8>=6.0.0; extra == "dev"
Requires-Dist: mypy>=1.0.0; extra == "dev"
Requires-Dist: pre-commit>=3.0.0; extra == "dev"
Requires-Dist: testcontainers[postgres,qdrant,redis]>=4.0.0; extra == "dev"
Requires-Dist: moto[s3]>=5.0.0; extra == "dev"
Dynamic: license-file
